[{"recipe_title":"초간단 야식 떡강정~*","recipe_url":"http://10000recipe.com/recipe/6937457","recipe_ingd":"떡볶이떡","recipe_time":"15분 이내","recipe_img":"https://recipe1.ezmember.co.kr/cache/recipe/2020/07/24/f5b8553f0cdc5641b64032f22f4cbae91.jpg","recipe_tag":"야식"},{"recipe_title":"시금치오믈렛 ♧ 치즈 들어간 초간단 야식 ♧","recipe_url":"http://10000recipe.com/recipe/6921432","recipe_ingd":"시금치\n달걀\n치즈","recipe_time":"5분 이내","recipe_img":"https://recipe1.ezmember.co.kr/cache/recipe/2019/10/30/6a5f26cd168f69b3656cdbb4d4d16e821.jpg","recipe_tag":"야식"},{"recipe_title":"편스토랑 박수홍 양념치킨 양념치밥 양념치킨소스 양념소스 후라이드 치킨 만드는 법 닭다리살 요리 술안주 야식","recipe_url":"http://10000recipe.com/recipe/6993738","recipe_ingd":"닭다리살\n다진마늘\n카레가루\n후추\n튀김가루","recipe_time":"60분 이내","recipe_img":"https://recipe1.ezmember.co.kr/cache/recipe/2022/12/13/1da26338d84a779a502b98bcd94726c71.jpg","recipe_tag":"야식"},{"recipe_title":"야식 추천 메뉴, 전자렌지 라볶이 레시피","recipe_url":"http://10000recipe.com/recipe/6901080","recipe_ingd":"컵라면\n떡볶이떡\n대파","recipe_time":"10분 이내","recipe_img":"https://recipe1.ezmember.co.kr/cache/recipe/2018/11/30/1accf917e80cf1ab85601f1fe80d38201.jpg","recipe_tag":"야식"},{"recipe_title":"간단 야식으로 스팸 유부초밥~*","recipe_url":"http://10000recipe.com/recipe/6937166","recipe_ingd":"스팸\n밥","recipe_time":"15분 이내","recipe_img":"https://recipe1.ezmember.co.kr/cache/recipe/2020/07/21/a08eb98eed9fb6986be0366e405601891.jpg","recipe_tag":"야식"},{"recipe_title":"야식엔 골뱅이소면 무침","recipe_url":"http://10000recipe.com/recipe/6843420","recipe_ingd":"골뱅이\n양파\n소면\n대파\n오이","recipe_time":"15분 이내","recipe_img":"https://recipe1.ezmember.co.kr/cache/recipe/2016/02/21/36e75de9f4913fb034843336e86f37f91.jpg","recipe_tag":"야식"},{"recipe_title":"야식으로 좋은 도토리묵사발","recipe_url":"http://10000recipe.com/recipe/6846868","recipe_ingd":"도토리묵\n냉면육수\n오이\n양파\n묵은지\n김도시락김\n양배추","recipe_time":"15분 이내","recipe_img":"https://recipe1.ezmember.co.kr/cache/recipe/2016/04/21/4b688acad2054ae8ef8f4e429258a88d1.jpg","recipe_tag":"야식"},{"recipe_title":"골뱅이 소면무침 오늘 야식","recipe_url":"http://10000recipe.com/recipe/6955128","recipe_ingd":"골뱅이통조림\n양파\n당근\n깻잎\n소면\n사과\n참기름\n진간장\n고추장\n고추가루\n설탕\n다진마늘\n식초\n참기름","recipe_time":"30분 이내","recipe_img":"https://recipe1.ezmember.co.kr/cache/recipe/2021/03/13/5af60e1331179ccefeb37a06d3f3337e1.jpg","recipe_tag":"야식"},{"recipe_title":"간단야식/팽이버섯전","recipe_url":"http://10000recipe.com/recipe/6888666","recipe_ingd":"팽이버섯\n달걀\n청양고추\n맛술\n소금\n후추\n부침유","recipe_time":"15분 이내","recipe_img":"https://recipe1.ezmember.co.kr/cache/recipe/2018/05/11/282fc2d92da5bdc08cf469502e5f94611.jpg","recipe_tag":"야식"},{"recipe_title":"떡꼬치소스에 무친 야식만들기! 맵달한 무침만두 ♥","recipe_url":"http://10000recipe.com/recipe/6960089","recipe_ingd":"만두\n식용유","recipe_time":"15분 이내","recipe_img":"https://recipe1.ezmember.co.kr/cache/recipe/2021/06/11/0cf417c97ad1f2eff6fa8f10d9a83fbd1.jpg","recipe_tag":"야식"},{"recipe_title":"심야식당 조개술찜 만들기","recipe_url":"http://10000recipe.com/recipe/6832079","recipe_ingd":"모시조개\n양파\n당근\n마늘\n청양고추\n버터\n간장\n화이트와인\n오징어\n파","recipe_time":"15분 이내","recipe_img":"https://recipe1.ezmember.co.kr/cache/recipe/2015/08/17/e89b283ca4b3f434829683a513548c691.jpg","recipe_tag":"야식"},{"recipe_title":"닭발요리~~ 초스피드 야식이 땡길땐 닭발볶음! 무뼈닭발 요리!","recipe_url":"http://10000recipe.com/recipe/6874485","recipe_ingd":"무뼈닭발\n양파\n대파\n깨","recipe_time":"60분 이내","recipe_img":"https://recipe1.ezmember.co.kr/cache/recipe/2017/08/10/baef20229c0996bd81b0441d45571e8c1.jpg","recipe_tag":"야식"},{"recipe_title":"정말 정말 초간단 마늘빵 만들기 야식으로도 굿!!!","recipe_url":"http://10000recipe.com/recipe/6889035","recipe_ingd":"식빵","recipe_time":"15분 이내","recipe_img":"https://recipe1.ezmember.co.kr/cache/recipe/2018/05/17/4e0f3bc0501e95119530fa7cde6ae1551.jpg","recipe_tag":"야식"},{"recipe_title":"야식&술안주, 바삭하고 고소한 녹두전 만들기","recipe_url":"http://10000recipe.com/recipe/6888477","recipe_ingd":"쌀한줌(쌀가루)\n돼지고기갈은것\n김치\n숙주","recipe_time":"60분 이내","recipe_img":"https://recipe1.ezmember.co.kr/cache/recipe/2018/05/08/df81cbd2a060ee79bc28959b7ab183871.jpg","recipe_tag":"야식"},{"recipe_title":"매운어묵떡볶이 야식으로 딱!!","recipe_url":"http://10000recipe.com/recipe/6992451","recipe_ingd":"밀떡\n어묵\n사각어묵\n물\n노랑파프리카\n빨강파프리카\n고구마\n양배추\n양파\n떡볶이양념장","recipe_time":"15분 이내","recipe_img":"https://recipe1.ezmember.co.kr/cache/recipe/2022/11/22/b93e51e2c5a27092c243c1dce592ba7b1.jpg","recipe_tag":"야식"},{"recipe_title":"마음까지 출출한 밤, 심야식당 조개술찜 따라하기 - 바지락 술찜 만들기","recipe_url":"http://10000recipe.com/recipe/6846999","recipe_ingd":"해감한바지락한팩\n청양고추\n쥐똥고추\n마늘\n청주\n버터\n간장","recipe_time":"15분 이내","recipe_img":"https://recipe1.ezmember.co.kr/cache/recipe/2016/04/24/512cfe0727592f3a30e07f769069b4771.jpg","recipe_tag":"야식"},{"recipe_title":"소주를 부르는 야식왕 순대볶음 ","recipe_url":"http://10000recipe.com/recipe/6888717","recipe_ingd":"순대\n양배추4분의\n양파\n깻잎","recipe_time":"15분 이내","recipe_img":"https://recipe1.ezmember.co.kr/cache/recipe/2018/05/11/14f3086644603ecaf1a3d0464fed2e361.jpg","recipe_tag":"야식"},{"recipe_title":"초간단 야식 전자렌지로 바삭한 라면땅 만들기","recipe_url":"http://10000recipe.com/recipe/6894563","recipe_ingd":"라면\n설탕\n라면스프","recipe_time":"5분 이내","recipe_img":"https://recipe1.ezmember.co.kr/cache/recipe/2018/08/22/c26b2be35cbef7939ecd38dcc6cd6a431.jpg","recipe_tag":"야식"},{"recipe_title":"야식으로 딱! 입맛돋구는 비빔칼국수만드는법 / 칼비빔면","recipe_url":"http://10000recipe.com/recipe/6888416","recipe_ingd":"계란\n상추\n칼국수면\n대패삼겹살","recipe_time":"15분 이내","recipe_img":"https://recipe1.ezmember.co.kr/cache/recipe/2018/05/07/720b9924f7a4821bc017dc548d2cf9dd1.jpg","recipe_tag":"야식"},{"recipe_title":"소떡소떡 만들기!간단하고 맛있는 야식!","recipe_url":"http://10000recipe.com/recipe/6894810","recipe_ingd":"비엔나소시지\n떡볶이떡","recipe_time":"30분 이내","recipe_img":"https://recipe1.ezmember.co.kr/cache/recipe/2018/08/26/f61cd7bf021776fab68e6c1841d0019d1.jpg","recipe_tag":"야식"},{"recipe_title":"초간단 골뱅이초무침, 골뱅이 무침, 즉석 안주, 야식","recipe_url":"http://10000recipe.com/recipe/6908440","recipe_ingd":"골뱅이\n양파(채썸)\n파(채썸)\n황태포","recipe_time":"15분 이내","recipe_img":"https://recipe1.ezmember.co.kr/cache/recipe/2019/03/15/9fc96477da7bf36a7a88d847e99a8f161.jpg","recipe_tag":"야식"},{"recipe_title":"주꾸미 볶음 야식 추천메뉴","recipe_url":"http://10000recipe.com/recipe/6888777","recipe_ingd":"주꾸미\n당근\n양파\n양배추\n청양고추\n홍고추\n대파\n밀가루\n굵은소금\n식용유","recipe_time":"30분 이내","recipe_img":"https://recipe1.ezmember.co.kr/cache/recipe/2018/05/14/e082caca11bc0e44b3efff02e76b9e631.jpg","recipe_tag":"야식"},{"recipe_title":"매콤한 야식 대패삼겹살 제육볶음 쉽게 만들기","recipe_url":"http://10000recipe.com/recipe/6936517","recipe_ingd":"대패삼겹살\n양파\n대파\n설탕\n참기름\n통깨","recipe_time":"15분 이내","recipe_img":"https://recipe1.ezmember.co.kr/cache/recipe/2020/07/13/b263c5a2d04a9ab0145a774be5eb86261.jpg","recipe_tag":"야식"},{"recipe_title":"야식으로 초간단 술안주 매콤한 번데기탕 만드는법.","recipe_url":"http://10000recipe.com/recipe/6888958","recipe_ingd":"번데기\n멸치육수\n대파\n마늘\n참치액젓\n고추가루\n청양고추","recipe_time":"15분 이내","recipe_img":"https://recipe1.ezmember.co.kr/cache/recipe/2018/04/02/5c0a40b56b41c56cd0601a125b56abe11.jpg","recipe_tag":"야식"},{"recipe_title":"골뱅이 쫄면 야식으로 최고죠!!","recipe_url":"http://10000recipe.com/recipe/6855186","recipe_ingd":"쫄면\n골뱅이","recipe_time":"30분 이내","recipe_img":"https://recipe1.ezmember.co.kr/cache/recipe/2016/08/23/9a7991843e8068b6955ae5d5eb191e521.jpg","recipe_tag":"야식"},{"recipe_title":"야식추천메뉴, 매콤한 볶음우동 만들기","recipe_url":"http://10000recipe.com/recipe/6888040","recipe_ingd":"우동면\n삼겹살\n새우살\n양파\n통마늘\n매운고추\n숙주\n파\n양송이버섯\n계란\n후추\n참기름\n깨\n가쓰오부시","recipe_time":"30분 이내","recipe_img":"https://recipe1.ezmember.co.kr/cache/recipe/2018/04/30/8aa230718dff4fbd564d8d39b60fa3611.jpg","recipe_tag":"야식"},{"recipe_title":"야식으로 튀기지 않은 양념치킨맛 닭조림 어떠세요?","recipe_url":"http://10000recipe.com/recipe/6936683","recipe_ingd":"닭다리살\n양파\n식용유","recipe_time":"60분 이내","recipe_img":"https://recipe1.ezmember.co.kr/cache/recipe/2020/07/15/a9bb1add7cbdad2fb8659f3e2f657d7f1.jpg","recipe_tag":"야식"},{"recipe_title":"야식이 필요할땐????!!!!! 편의점표 달걀참치콘전 ★","recipe_url":"http://10000recipe.com/recipe/6917514","recipe_ingd":"달걀\n참치\n옥수수콘\n소금\n후추","recipe_time":"10분 이내","recipe_img":"https://recipe1.ezmember.co.kr/cache/recipe/2019/08/13/1e81d3b944f6493f4b25a4909c11d4581.jpg","recipe_tag":"야식"},{"recipe_title":"에어프라이어 요리추천 아코디언 감자칩 튀김간식 맥주안주 야식레시피","recipe_url":"http://10000recipe.com/recipe/6993632","recipe_ingd":"감자\n소금\n파슬리가루\n버터","recipe_time":"30분 이내","recipe_img":"https://recipe1.ezmember.co.kr/cache/recipe/2022/12/12/38214afee6ac4c118b1cbf2bb88a43631.jpg","recipe_tag":"야식"},{"recipe_title":"야식으로도 좋은 게살스프 간단한재료로 근사하게~*","recipe_url":"http://10000recipe.com/recipe/6888710","recipe_ingd":"크래미\n치킨스톡(없을경우요리팁참고)\n계란\n전분가루\n버섯\n후추","recipe_time":"10분 이내","recipe_img":"https://recipe1.ezmember.co.kr/cache/recipe/2018/05/11/3746422332c117da5a2fb22cd644295a1.jpg","recipe_tag":"야식"},{"recipe_title":"간단한 야식 '비빔만두' 만들기","recipe_url":"http://10000recipe.com/recipe/6869584","recipe_ingd":"냉동만두\n양배추\n당근\n깻잎\n김가루\n식용유","recipe_time":"30분 이내","recipe_img":"https://recipe1.ezmember.co.kr/cache/recipe/2017/05/10/65378484b5fa45265602907588202d2e1.jpg","recipe_tag":"야식"},{"recipe_title":"야식하면 라면 .김치 콩나물 넣어 아삭하게~","recipe_url":"http://10000recipe.com/recipe/6888740","recipe_ingd":"라면\n대파\n콩나물\n김치","recipe_time":"15분 이내","recipe_img":"https://recipe1.ezmember.co.kr/cache/recipe/2018/05/12/4318f8413ea8ea46b8b00f94304079661.jpg","recipe_tag":"야식"},{"recipe_title":"닭가슴살튀김 # 심야식당 카라아게","recipe_url":"http://10000recipe.com/recipe/6844289","recipe_ingd":"닭가슴살\n허브솔트\n간마늘\n간장\n생강가루\n전분가루\n계란","recipe_time":"30분 이내","recipe_img":"https://recipe1.ezmember.co.kr/cache/recipe/2016/03/08/519adcce057501b0bb4848a7b8d08d421.jpg","recipe_tag":"야식"},{"recipe_title":"에어프라이어요리 추천 웨지감자 안주야식 아이간식 버터튀김만들기","recipe_url":"http://10000recipe.com/recipe/6992809","recipe_ingd":"감자\n파슬리가루\n올리브유\n후추\n소금\n설탕","recipe_time":"15분 이내","recipe_img":"https://recipe1.ezmember.co.kr/cache/recipe/2022/11/28/dfefb56d1d8b66cae9f2fc6c08ce4f8c1.jpg","recipe_tag":"야식"},{"recipe_title":"그냥 잡채도 맛나지만 야식으로는 매콤한게 짱이지!! 김치볶음잡채★","recipe_url":"http://10000recipe.com/recipe/6860847","recipe_ingd":"김치\n당면\n양파","recipe_time":"10분 이내","recipe_img":"https://recipe1.ezmember.co.kr/cache/recipe/2016/11/16/a82cc727c5fbc23f132cc4790d060c161.png","recipe_tag":"야식"},{"recipe_title":"야식으로 좋은 백종원 볶음라면","recipe_url":"http://10000recipe.com/recipe/6834137","recipe_ingd":"라면\n대파\n달걀","recipe_time":"10분 이내","recipe_img":"https://recipe1.ezmember.co.kr/cache/recipe/2015/09/11/fe0a2943fbd1f2e2df212845eeeef0c81.jpg","recipe_tag":"야식"},{"recipe_title":"소고기말이 단짠하게 만들어 본 소고기야채말이 야식으로 굿~","recipe_url":"http://10000recipe.com/recipe/6888520","recipe_ingd":"소고기(불고기감)\n노랑파프리카\n피망\n새송이버섯\n소금\n후추\n간장\n맛술\n올리고당\n매실액\n참기름\n마늘\n찹쌀가루","recipe_time":"30분 이내","recipe_img":"https://recipe1.ezmember.co.kr/cache/recipe/2018/05/08/1b83c25dbe9a024a497afb9d61ba1ffb1.jpg","recipe_tag":"야식"},{"recipe_title":"야식으로 딱! 쫄깃한 닭똥집 볶음 만들기","recipe_url":"http://10000recipe.com/recipe/6837968","recipe_ingd":"닭똥집\n통마늘\n청량고추","recipe_time":"60분 이내","recipe_img":"https://recipe1.ezmember.co.kr/cache/recipe/2015/11/11/d8f3c069729de45192a2e4816a8ecd2b1.jpg","recipe_tag":"야식"},{"recipe_title":"야식에는 대패삼겹살 굴소스 숙주볶음 ","recipe_url":"http://10000recipe.com/recipe/6846695","recipe_ingd":"대패삼겹살\n숙주나물\n대파\n팽이버섯\n청양고추\n다진마늘","recipe_time":"15분 이내","recipe_img":"https://recipe1.ezmember.co.kr/cache/recipe/2016/04/19/24d38ff130696396f3a86fb8cd1256ed1.jpg","recipe_tag":"야식"},{"recipe_title":"【초간단】 야식 비빔국수 만들기","recipe_url":"http://10000recipe.com/recipe/6867157","recipe_ingd":"국수\n양파\n오이\n깻잎\n마늘","recipe_time":"10분 이내","recipe_img":"https://recipe1.ezmember.co.kr/cache/recipe/2017/03/21/a640f519093bf7804bdc46379bf890031.jpg","recipe_tag":"야식"}]